ruobr_api/__init__.py
ruobr_api/__main__.py
ruobr_api/exceptions.py
ruobr_api-2.0.2.dist-info/LICENSE
ruobr_api-2.0.2.dist-info/METADATA
ruobr_api-2.0.2.dist-info/WHEEL
ruobr_api-2.0.2.dist-info/top_level.txt
ruobr_api-2.0.2.dist-info/RECORD
