Metadata-Version: 2.1
Name: ruobr-api
Version: 2.0.2
Summary: Python модуль для доступа к API электронного дневника Кемеровской области (cabinet.ruobr.ru API wrapper)
Home-page: https://github.com/raitonoberu/ruobr_api
Author: raitonoberu
Author-email: raitonoberu@mail.ru
License: Apache License, Version 2.0, see LICENSE file
Download-URL: https://github.com/raitonoberu/ruobr_api/archive/2.0.2.zip
Platform: UNKNOWN
Classifier: Intended Audience :: Developers
Classifier: License :: OSI Approved :: Apache Software License
Classifier: Operating System :: OS Independent
Classifier: Programming Language :: Python
Classifier: Programming Language :: Python :: 3
Classifier: Programming Language :: Python :: 3.6
Classifier: Programming Language :: Python :: 3.7
Classifier: Programming Language :: Python :: 3.8
License-File: LICENSE
Requires-Dist: httpx
